trabalho_jeansilva_converter_csv_json/__init__.py
trabalho_jeansilva_converter_csv_json/converter.py
trabalho_jeansilva_converter_csv_json-0.1.5.dist-info/entry_points.txt
trabalho_jeansilva_converter_csv_json-0.1.5.dist-info/WHEEL
trabalho_jeansilva_converter_csv_json-0.1.5.dist-info/METADATA
trabalho_jeansilva_converter_csv_json-0.1.5.dist-info/RECORD
